Workbook

Sheet Dashboard
A1: LEGION CLUB / CARO LEGION S.L. - Panel para financiación e inversores
A3: Versión base de trabajo: los datos amarillos del libro deben sustituirse por datos reales antes de presentar a terceros.
A5: Resumen BASE | F5: Lectura rápida
A6: Importe buscado | B6: =Inputs!$B$6 | C6: € | D6: Cantidad a pedir. | F6: Punto muerto aproximado | G6: =(Inputs!$B$16+Inputs!$B$17+Inputs!$C$30)/(Inputs!$C$27/(1+Inputs!$B$12)-Inputs!$C$29) | H6: socios
A7: Pre-money propuesta | B7: =Inputs!$B$7 | C7: € | D7: Valoración antes de inversión. | F7: Deuda simulada | G7: =Inputs!$B$6 | H7: €
A8: % inversor estimado | B8: =Inputs!$B$6/(Inputs!$B$6+Inputs!$B$7) | C8: % | D8: Si entra como capital. | F8: Pago mensual post-carencia | G8: =-PMT(Inputs!$B$9/12,Inputs!$B$10-Inputs!$B$11,Inputs!$B$6) | H8: €/mes
A9: Socios mes 12 | B9: =Socios_36M!C15 | C9: socios | D9: Escenario base. | F9: Post-money simulado | G9: =Inputs!$B$6+Inputs!$B$7 | H9: €
A10: Socios mes 24 | B10: =Socios_36M!C27 | C10: socios | D10: Escenario base.
A11: Socios mes 36 | B11: =Socios_36M!C39 | C11: socios | D11: Escenario base.
A12: Ingresos netos mes 12 | B12: =PnL_36M!E15 | C12: € | D12: Sin IVA.
A13: EBITDA mes 12 | B13: =PnL_36M!J15 | C13: € | D13: Antes de deuda/capex.
A14: EBITDA mes 36 | B14: =PnL_36M!J39 | C14: € | D14: Estabilizado orientativo.
A15: Caja acumulada mes 36 | B15: =Caja_Deuda!J39 | C15: € | D15: Después de capex y deuda.
A16: Valoración base sugerida | B16: =Valoracion!C9 | C16: € | D16: Promedio de métodos.

Sheet Inputs
A1: Modelo financiero LEGION - Supuestos editables
A3: Cómo usar esta hoja: las celdas amarillas/azules son supuestos editables. Las fórmulas tiran de estos datos. Sustituye los valores por los reales antes de enseñar el modelo a prestamistas o inversores.
A5: Financiación y valoración
A6: Importe buscado | B6: 245474 | E6: € | F6: Editable: dinero que quieres pedir ahora.
A7: Valoración pre-money propuesta | B7: 500000 | E7: € | F7: Borrador prudente para simular entrada de inversor; debe validarse.
A8: Caja inicial disponible | B8: 63246 | E8: € | F8: Introduce tesorería real antes de apertura.
A9: Tipo interés préstamo anual | B9: 0.06 | E9: % | F9: Supuesto editable para préstamo privado.
A10: Plazo préstamo | B10: 84 | E10: meses | F10: Plazo total de devolución.
A11: Carencia préstamo | B11: 12 | E11: meses | F11: Meses sin amortizar capital.
A12: IVA aplicable | B12: 0.21 | E12: % | F12: Validar con gestoría antes de enviar.
A13: Impuesto sociedades | B13: 0.25 | E13: % | F13: Validar con gestoría; no se aplica en todos los cálculos.
A15: Costes y activos conocidos
A16: Coste fijo operativo mensual objetivo | B16: 9000 | E16: €/mes | F16: Real estimado: alquiler (2.600) + personal minimo (Sergi+2) + servicios/seguros/gestoria.
A17: Renting maquinaria mensual | B17: 0 | E17: €/mes | F17: La maquinaria es propiedad de la sociedad (comprada), no hay renting.
A18: Inversión pendiente antes de abrir | B18: 308720 | E18: € | F18: Real: total pendiente de pago segun control de obra (climatizacion, electrica, maquinaria, vestuarios, accesos).
A19: Inversión socios / fondos aportados | B19: 180750 | E19: € | F19: Real: inversion ya ejecutada y pagada por los socios (banco), a fecha de este documento.
A20: Activos/compromisos identificados | B20: 106008 | E20: € | F20: Real: maquinaria HSE 85.438 EUR (pagado+pendiente) + suelo/pavimento 20.570 EUR.
A21: Valor intangible preapertura | B21: 25000 | E21: € | F21: Estimacion prudente: marca, 230 preinscripciones, app, proveedores.
A23: Escenarios de socios e ingresos | B23: Conservador | C23: Base | D23: Optimista | E23: Unidad | F23: Nota
A24: Socios iniciales mes 1 | B24: 180 | C24: 230 | D24: 260 | E24: socios | F24: Real: 230 preinscritos a la fecha (sigue creciendo, aun sin abrir). Facturan desde el dia 1 de apertura.
A25: Altas brutas mensuales | B25: 30 | C25: 45 | D25: 60 | E25: socios/mes | F25: Nuevas altas antes de bajas.
A26: Baja/churn mensual | B26: 0.045 | C26: 0.03 | D26: 0.02 | E26: % | F26: Porcentaje de socios que se dan de baja cada mes.
A27: Cuota media mensual IVA incluido | B27: 42 | C27: 50 | D27: 55 | E27: €/socio/mes | F27: Base 50 EUR/mes IVA incl., consistente con el resto de documentos del proyecto.
A28: Ingresos extra medios IVA incluido | B28: 2 | C28: 4 | D28: 6 | E28: €/socio/mes | F28: Vending, coaching, extras prorrateados. Ajustar.
A29: Coste variable por socio | B29: 3 | C29: 4 | D29: 5 | E29: €/socio/mes | F29: Comisiones, limpieza variable, consumibles, etc.
A30: Marketing mensual recurrente | B30: 1500 | C30: 2000 | D30: 2500 | E30: €/mes | F30: Después del lanzamiento.
A31: Capacidad máxima realista | B31: 800 | C31: 1200 | D31: 1500 | E31: socios | F31: No confundir con capacidad física absoluta.
A32: Múltiplo EBITDA salida | B32: 3 | C32: 4 | D32: 5 | E32: x | F32: Para valoración por EBITDA estabilizado.
A33: Tasa descuento anual | B33: 0.3 | C33: 0.25 | D33: 0.22 | E33: % | F33: Riesgo alto por fase preapertura.
A34: Múltiplo ingresos anuales | B34: 0.6 | C34: 0.9 | D34: 1.2 | E34: x | F34: Benchmark interno orientativo, no externo.

Sheet Socios_36M
A1: Evolución de socios activos por escenario - 36 meses
A3: Mes | B3: Conservador | C3: Base | D3: Optimista
A4: 1 | B4: =Inputs!B$24 | C4: =Inputs!C$24 | D4: =Inputs!D$24
A5: 2 | B5: =MIN(Inputs!B$31,ROUND(B4*(1-Inputs!B$26)+Inputs!B$25,0)) | C5: =MIN(Inputs!C$31,ROUND(C4*(1-Inputs!C$26)+Inputs!C$25,0)) | D5: =MIN(Inputs!D$31,ROUND(D4*(1-Inputs!D$26)+Inputs!D$25,0))
A6: 3 | B6: =MIN(Inputs!B$31,ROUND(B5*(1-Inputs!B$26)+Inputs!B$25,0)) | C6: =MIN(Inputs!C$31,ROUND(C5*(1-Inputs!C$26)+Inputs!C$25,0)) | D6: =MIN(Inputs!D$31,ROUND(D5*(1-Inputs!D$26)+Inputs!D$25,0))
A7: 4 | B7: =MIN(Inputs!B$31,ROUND(B6*(1-Inputs!B$26)+Inputs!B$25,0)) | C7: =MIN(Inputs!C$31,ROUND(C6*(1-Inputs!C$26)+Inputs!C$25,0)) | D7: =MIN(Inputs!D$31,ROUND(D6*(1-Inputs!D$26)+Inputs!D$25,0))
A8: 5 | B8: =MIN(Inputs!B$31,ROUND(B7*(1-Inputs!B$26)+Inputs!B$25,0)) | C8: =MIN(Inputs!C$31,ROUND(C7*(1-Inputs!C$26)+Inputs!C$25,0)) | D8: =MIN(Inputs!D$31,ROUND(D7*(1-Inputs!D$26)+Inputs!D$25,0))
A9: 6 | B9: =MIN(Inputs!B$31,ROUND(B8*(1-Inputs!B$26)+Inputs!B$25,0)) | C9: =MIN(Inputs!C$31,ROUND(C8*(1-Inputs!C$26)+Inputs!C$25,0)) | D9: =MIN(Inputs!D$31,ROUND(D8*(1-Inputs!D$26)+Inputs!D$25,0))
A10: 7 | B10: =MIN(Inputs!B$31,ROUND(B9*(1-Inputs!B$26)+Inputs!B$25,0)) | C10: =MIN(Inputs!C$31,ROUND(C9*(1-Inputs!C$26)+Inputs!C$25,0)) | D10: =MIN(Inputs!D$31,ROUND(D9*(1-Inputs!D$26)+Inputs!D$25,0))
A11: 8 | B11: =MIN(Inputs!B$31,ROUND(B10*(1-Inputs!B$26)+Inputs!B$25,0)) | C11: =MIN(Inputs!C$31,ROUND(C10*(1-Inputs!C$26)+Inputs!C$25,0)) | D11: =MIN(Inputs!D$31,ROUND(D10*(1-Inputs!D$26)+Inputs!D$25,0))
A12: 9 | B12: =MIN(Inputs!B$31,ROUND(B11*(1-Inputs!B$26)+Inputs!B$25,0)) | C12: =MIN(Inputs!C$31,ROUND(C11*(1-Inputs!C$26)+Inputs!C$25,0)) | D12: =MIN(Inputs!D$31,ROUND(D11*(1-Inputs!D$26)+Inputs!D$25,0))
A13: 10 | B13: =MIN(Inputs!B$31,ROUND(B12*(1-Inputs!B$26)+Inputs!B$25,0)) | C13: =MIN(Inputs!C$31,ROUND(C12*(1-Inputs!C$26)+Inputs!C$25,0)) | D13: =MIN(Inputs!D$31,ROUND(D12*(1-Inputs!D$26)+Inputs!D$25,0))
A14: 11 | B14: =MIN(Inputs!B$31,ROUND(B13*(1-Inputs!B$26)+Inputs!B$25,0)) | C14: =MIN(Inputs!C$31,ROUND(C13*(1-Inputs!C$26)+Inputs!C$25,0)) | D14: =MIN(Inputs!D$31,ROUND(D13*(1-Inputs!D$26)+Inputs!D$25,0))
A15: 12 | B15: =MIN(Inputs!B$31,ROUND(B14*(1-Inputs!B$26)+Inputs!B$25,0)) | C15: =MIN(Inputs!C$31,ROUND(C14*(1-Inputs!C$26)+Inputs!C$25,0)) | D15: =MIN(Inputs!D$31,ROUND(D14*(1-Inputs!D$26)+Inputs!D$25,0))
A16: 13 | B16: =MIN(Inputs!B$31,ROUND(B15*(1-Inputs!B$26)+Inputs!B$25,0)) | C16: =MIN(Inputs!C$31,ROUND(C15*(1-Inputs!C$26)+Inputs!C$25,0)) | D16: =MIN(Inputs!D$31,ROUND(D15*(1-Inputs!D$26)+Inputs!D$25,0))
... A39: 36 | B39: =MIN(Inputs!B$31,ROUND(B38*(1-Inputs!B$26)+Inputs!B$25,0)) | C39: =MIN(Inputs!C$31,ROUND(C38*(1-Inputs!C$26)+Inputs!C$25,0)) | D39: =MIN(Inputs!D$31,ROUND(D38*(1-Inputs!D$26)+Inputs!D$25,0))

Sheet PnL_36M
A1: Cuenta de resultados mensual - Escenario BASE
A3: Mes | B3: Socios activos | C3: Ingresos cuotas netos | D3: Ingresos extra netos | E3: Ingresos netos | F3: Coste variable | G3: Costes fijos | H3: Renting maquinaria | I3: Marketing | J3: EBITDA | K3: Margen EBITDA | L3: EBITDA acumulado | M3: Nota
A4: 1 | B4: =Socios_36M!C4 | C4: =B4*Inputs!$C$27/(1+Inputs!$B$12) | D4: =B4*Inputs!$C$28/(1+Inputs!$B$12) | E4: =C4+D4 | F4: =B4*Inputs!$C$29 | G4: =Inputs!$B$16 | H4: =Inputs!$B$17 | I4: =Inputs!$C$30 | J4: =E4-F4-G4-H4-I4 | K4: =IFERROR(J4/E4,0) | L4: =SUM($J$4:J4)
A5: 2 | B5: =Socios_36M!C5 | C5: =B5*Inputs!$C$27/(1+Inputs!$B$12) | D5: =B5*Inputs!$C$28/(1+Inputs!$B$12) | E5: =C5+D5 | F5: =B5*Inputs!$C$29 | G5: =Inputs!$B$16 | H5: =Inputs!$B$17 | I5: =Inputs!$C$30 | J5: =E5-F5-G5-H5-I5 | K5: =IFERROR(J5/E5,0) | L5: =SUM($J$4:J5)
A6: 3 | B6: =Socios_36M!C6 | C6: =B6*Inputs!$C$27/(1+Inputs!$B$12) | D6: =B6*Inputs!$C$28/(1+Inputs!$B$12) | E6: =C6+D6 | F6: =B6*Inputs!$C$29 | G6: =Inputs!$B$16 | H6: =Inputs!$B$17 | I6: =Inputs!$C$30 | J6: =E6-F6-G6-H6-I6 | K6: =IFERROR(J6/E6,0) | L6: =SUM($J$4:J6)
A7: 4 | B7: =Socios_36M!C7 | C7: =B7*Inputs!$C$27/(1+Inputs!$B$12) | D7: =B7*Inputs!$C$28/(1+Inputs!$B$12) | E7: =C7+D7 | F7: =B7*Inputs!$C$29 | G7: =Inputs!$B$16 | H7: =Inputs!$B$17 | I7: =Inputs!$C$30 | J7: =E7-F7-G7-H7-I7 | K7: =IFERROR(J7/E7,0) | L7: =SUM($J$4:J7)
A8: 5 | B8: =Socios_36M!C8 | C8: =B8*Inputs!$C$27/(1+Inputs!$B$12) | D8: =B8*Inputs!$C$28/(1+Inputs!$B$12) | E8: =C8+D8 | F8: =B8*Inputs!$C$29 | G8: =Inputs!$B$16 | H8: =Inputs!$B$17 | I8: =Inputs!$C$30 | J8: =E8-F8-G8-H8-I8 | K8: =IFERROR(J8/E8,0) | L8: =SUM($J$4:J8)
A9: 6 | B9: =Socios_36M!C9 | C9: =B9*Inputs!$C$27/(1+Inputs!$B$12) | D9: =B9*Inputs!$C$28/(1+Inputs!$B$12) | E9: =C9+D9 | F9: =B9*Inputs!$C$29 | G9: =Inputs!$B$16 | H9: =Inputs!$B$17 | I9: =Inputs!$C$30 | J9: =E9-F9-G9-H9-I9 | K9: =IFERROR(J9/E9,0) | L9: =SUM($J$4:J9)
A10: 7 | B10: =Socios_36M!C10 | C10: =B10*Inputs!$C$27/(1+Inputs!$B$12) | D10: =B10*Inputs!$C$28/(1+Inputs!$B$12) | E10: =C10+D10 | F10: =B10*Inputs!$C$29 | G10: =Inputs!$B$16 | H10: =Inputs!$B$17 | I10: =Inputs!$C$30 | J10: =E10-F10-G10-H10-I10 | K10: =IFERROR(J10/E10,0) | L10: =SUM($J$4:J10)
A11: 8 | B11: =Socios_36M!C11 | C11: =B11*Inputs!$C$27/(1+Inputs!$B$12) | D11: =B11*Inputs!$C$28/(1+Inputs!$B$12) | E11: =C11+D11 | F11: =B11*Inputs!$C$29 | G11: =Inputs!$B$16 | H11: =Inputs!$B$17 | I11: =Inputs!$C$30 | J11: =E11-F11-G11-H11-I11 | K11: =IFERROR(J11/E11,0) | L11: =SUM($J$4:J11)
A12: 9 | B12: =Socios_36M!C12 | C12: =B12*Inputs!$C$27/(1+Inputs!$B$12) | D12: =B12*Inputs!$C$28/(1+Inputs!$B$12) | E12: =C12+D12 | F12: =B12*Inputs!$C$29 | G12: =Inputs!$B$16 | H12: =Inputs!$B$17 | I12: =Inputs!$C$30 | J12: =E12-F12-G12-H12-I12 | K12: =IFERROR(J12/E12,0) | L12: =SUM($J$4:J12)
A13: 10 | B13: =Socios_36M!C13 | C13: =B13*Inputs!$C$27/(1+Inputs!$B$12) | D13: =B13*Inputs!$C$28/(1+Inputs!$B$12) | E13: =C13+D13 | F13: =B13*Inputs!$C$29 | G13: =Inputs!$B$16 | H13: =Inputs!$B$17 | I13: =Inputs!$C$30 | J13: =E13-F13-G13-H13-I13 | K13: =IFERROR(J13/E13,0) | L13: =SUM($J$4:J13)
A14: 11 | B14: =Socios_36M!C14 | C14: =B14*Inputs!$C$27/(1+Inputs!$B$12) | D14: =B14*Inputs!$C$28/(1+Inputs!$B$12) | E14: =C14+D14 | F14: =B14*Inputs!$C$29 | G14: =Inputs!$B$16 | H14: =Inputs!$B$17 | I14: =Inputs!$C$30 | J14: =E14-F14-G14-H14-I14 | K14: =IFERROR(J14/E14,0) | L14: =SUM($J$4:J14)
A15: 12 | B15: =Socios_36M!C15 | C15: =B15*Inputs!$C$27/(1+Inputs!$B$12) | D15: =B15*Inputs!$C$28/(1+Inputs!$B$12) | E15: =C15+D15 | F15: =B15*Inputs!$C$29 | G15: =Inputs!$B$16 | H15: =Inputs!$B$17 | I15: =Inputs!$C$30 | J15: =E15-F15-G15-H15-I15 | K15: =IFERROR(J15/E15,0) | L15: =SUM($J$4:J15)
... A39: 36 | B39: =Socios_36M!C39 | C39: =B39*Inputs!$C$27/(1+Inputs!$B$12) | D39: =B39*Inputs!$C$28/(1+Inputs!$B$12) | E39: =C39+D39 | F39: =B39*Inputs!$C$29 | G39: =Inputs!$B$16 | H39: =Inputs!$B$17 | I39: =Inputs!$C$30 | J39: =E39-F39-G39-H39-I39 | K39: =IFERROR(J39/E39,0) | L39: =SUM($J$4:J39)

Sheet Caja_Deuda
A1: Cash flow y préstamo privado - Escenario BASE
A3: Mes | B3: EBITDA | C3: Capex pendiente | D3: Saldo inicial deuda | E3: Interés | F3: Pago total | G3: Amortización capital | H3: Saldo final deuda | I3: Cash flow mensual | J3: Caja acumulada | K3: Nota | L3: Entrada de préstamo
A4: 1 | B4: =PnL_36M!J4 | C4: =IF(A4=1,Inputs!$B$18,0) | D4: =Inputs!$B$6 | E4: =D4*Inputs!$B$9/12 | F4: =IF(A4<=Inputs!$B$11,E4,MIN(D4+E4,-PMT(Inputs!$B$9/12,Inputs!$B$10-Inputs!$B$11,Inputs!$B$6))) | G4: =MAX(0,F4-E4) | H4: =MAX(0,D4-G4) | I4: =B4-C4-F4+L4 | J4: =Inputs!$B$8+I4 | L4: =IF(A4=1,Inputs!$B$6,0)
A5: 2 | B5: =PnL_36M!J5 | C5: =IF(A5=1,Inputs!$B$18,0) | D5: =H4 | E5: =D5*Inputs!$B$9/12 | F5: =IF(A5<=Inputs!$B$11,E5,MIN(D5+E5,-PMT(Inputs!$B$9/12,Inputs!$B$10-Inputs!$B$11,Inputs!$B$6))) | G5: =MAX(0,F5-E5) | H5: =MAX(0,D5-G5) | I5: =B5-C5-F5+L5 | J5: =J4+I5 | L5: =IF(A5=1,Inputs!$B$6,0)
A6: 3 | B6: =PnL_36M!J6 | C6: =IF(A6=1,Inputs!$B$18,0) | D6: =H5 | E6: =D6*Inputs!$B$9/12 | F6: =IF(A6<=Inputs!$B$11,E6,MIN(D6+E6,-PMT(Inputs!$B$9/12,Inputs!$B$10-Inputs!$B$11,Inputs!$B$6))) | G6: =MAX(0,F6-E6) | H6: =MAX(0,D6-G6) | I6: =B6-C6-F6+L6 | J6: =J5+I6 | L6: =IF(A6=1,Inputs!$B$6,0)
A7: 4 | B7: =PnL_36M!J7 | C7: =IF(A7=1,Inputs!$B$18,0) | D7: =H6 | E7: =D7*Inputs!$B$9/12 | F7: =IF(A7<=Inputs!$B$11,E7,MIN(D7+E7,-PMT(Inputs!$B$9/12,Inputs!$B$10-Inputs!$B$11,Inputs!$B$6))) | G7: =MAX(0,F7-E7) | H7: =MAX(0,D7-G7) | I7: =B7-C7-F7+L7 | J7: =J6+I7 | L7: =IF(A7=1,Inputs!$B$6,0)
A8: 5 | B8: =PnL_36M!J8 | C8: =IF(A8=1,Inputs!$B$18,0) | D8: =H7 | E8: =D8*Inputs!$B$9/12 | F8: =IF(A8<=Inputs!$B$11,E8,MIN(D8+E8,-PMT(Inputs!$B$9/12,Inputs!$B$10-Inputs!$B$11,Inputs!$B$6))) | G8: =MAX(0,F8-E8) | H8: =MAX(0,D8-G8) | I8: =B8-C8-F8+L8 | J8: =J7+I8 | L8: =IF(A8=1,Inputs!$B$6,0)
A9: 6 | B9: =PnL_36M!J9 | C9: =IF(A9=1,Inputs!$B$18,0) | D9: =H8 | E9: =D9*Inputs!$B$9/12 | F9: =IF(A9<=Inputs!$B$11,E9,MIN(D9+E9,-PMT(Inputs!$B$9/12,Inputs!$B$10-Inputs!$B$11,Inputs!$B$6))) | G9: =MAX(0,F9-E9) | H9: =MAX(0,D9-G9) | I9: =B9-C9-F9+L9 | J9: =J8+I9 | L9: =IF(A9=1,Inputs!$B$6,0)
A10: 7 | B10: =PnL_36M!J10 | C10: =IF(A10=1,Inputs!$B$18,0) | D10: =H9 | E10: =D10*Inputs!$B$9/12 | F10: =IF(A10<=Inputs!$B$11,E10,MIN(D10+E10,-PMT(Inputs!$B$9/12,Inputs!$B$10-Inputs!$B$11,Inputs!$B$6))) | G10: =MAX(0,F10-E10) | H10: =MAX(0,D10-G10) | I10: =B10-C10-F10+L10 | J10: =J9+I10 | L10: =IF(A10=1,Inputs!$B$6,0)
A11: 8 | B11: =PnL_36M!J11 | C11: =IF(A11=1,Inputs!$B$18,0) | D11: =H10 | E11: =D11*Inputs!$B$9/12 | F11: =IF(A11<=Inputs!$B$11,E11,MIN(D11+E11,-PMT(Inputs!$B$9/12,Inputs!$B$10-Inputs!$B$11,Inputs!$B$6))) | G11: =MAX(0,F11-E11) | H11: =MAX(0,D11-G11) | I11: =B11-C11-F11+L11 | J11: =J10+I11 | L11: =IF(A11=1,Inputs!$B$6,0)
A12: 9 | B12: =PnL_36M!J12 | C12: =IF(A12=1,Inputs!$B$18,0) | D12: =H11 | E12: =D12*Inputs!$B$9/12 | F12: =IF(A12<=Inputs!$B$11,E12,MIN(D12+E12,-PMT(Inputs!$B$9/12,Inputs!$B$10-Inputs!$B$11,Inputs!$B$6))) | G12: =MAX(0,F12-E12) | H12: =MAX(0,D12-G12) | I12: =B12-C12-F12+L12 | J12: =J11+I12 | L12: =IF(A12=1,Inputs!$B$6,0)
A13: 10 | B13: =PnL_36M!J13 | C13: =IF(A13=1,Inputs!$B$18,0) | D13: =H12 | E13: =D13*Inputs!$B$9/12 | F13: =IF(A13<=Inputs!$B$11,E13,MIN(D13+E13,-PMT(Inputs!$B$9/12,Inputs!$B$10-Inputs!$B$11,Inputs!$B$6))) | G13: =MAX(0,F13-E13) | H13: =MAX(0,D13-G13) | I13: =B13-C13-F13+L13 | J13: =J12+I13 | L13: =IF(A13=1,Inputs!$B$6,0)
A14: 11 | B14: =PnL_36M!J14 | C14: =IF(A14=1,Inputs!$B$18,0) | D14: =H13 | E14: =D14*Inputs!$B$9/12 | F14: =IF(A14<=Inputs!$B$11,E14,MIN(D14+E14,-PMT(Inputs!$B$9/12,Inputs!$B$10-Inputs!$B$11,Inputs!$B$6))) | G14: =MAX(0,F14-E14) | H14: =MAX(0,D14-G14) | I14: =B14-C14-F14+L14 | J14: =J13+I14 | L14: =IF(A14=1,Inputs!$B$6,0)
A15: 12 | B15: =PnL_36M!J15 | C15: =IF(A15=1,Inputs!$B$18,0) | D15: =H14 | E15: =D15*Inputs!$B$9/12 | F15: =IF(A15<=Inputs!$B$11,E15,MIN(D15+E15,-PMT(Inputs!$B$9/12,Inputs!$B$10-Inputs!$B$11,Inputs!$B$6))) | G15: =MAX(0,F15-E15) | H15: =MAX(0,D15-G15) | I15: =B15-C15-F15+L15 | J15: =J14+I15 | L15: =IF(A15=1,Inputs!$B$6,0)
A16: 13 | B16: =PnL_36M!J16 | C16: =IF(A16=1,Inputs!$B$18,0) | D16: =H15 | E16: =D16*Inputs!$B$9/12 | F16: =IF(A16<=Inputs!$B$11,E16,MIN(D16+E16,-PMT(Inputs!$B$9/12,Inputs!$B$10-Inputs!$B$11,Inputs!$B$6))) | G16: =MAX(0,F16-E16) | H16: =MAX(0,D16-G16) | I16: =B16-C16-F16+L16 | J16: =J15+I16 | L16: =IF(A16=1,Inputs!$B$6,0)
... A39: 36 | B39: =PnL_36M!J39 | C39: =IF(A39=1,Inputs!$B$18,0) | D39: =H38 | E39: =D39*Inputs!$B$9/12 | F39: =IF(A39<=Inputs!$B$11,E39,MIN(D39+E39,-PMT(Inputs!$B$9/12,Inputs!$B$10-Inputs!$B$11,Inputs!$B$6))) | G39: =MAX(0,F39-E39) | H39: =MAX(0,D39-G39) | I39: =B39-C39-F39+L39 | J39: =J38+I39 | L39: =IF(A39=1,Inputs!$B$6,0)

Sheet Valoracion
A1: Valoración económica - Rango orientativo editable
A3: Método | B3: Conservador | C3: Base | D3: Optimista | E3: Unidad | F3: Comentario
A4: Coste de reposición | B4: =Inputs!$B$19+Inputs!$B$20+Inputs!$B$21 | C4: =Inputs!$B$19+Inputs!$B$20+Inputs!$B$21 | D4: =Inputs!$B$19+Inputs!$B$20+Inputs!$B$21 | E4: € | F4: Inversión aportada + activos + intangible prudente.
A5: Ingresos año 3 anualizados | B5: =Socios_36M!B$39*(Inputs!B$27+Inputs!B$28)/(1+Inputs!$B$12)*12 | C5: =Socios_36M!C$39*(Inputs!C$27+Inputs!C$28)/(1+Inputs!$B$12)*12 | D5: =Socios_36M!D$39*(Inputs!D$27+Inputs!D$28)/(1+Inputs!$B$12)*12 | E5: € | F5: Mes 36 x 12; base en ingresos netos.
A6: Valor por múltiplo de ingresos | B6: =B5*Inputs!B$34 | C6: =C5*Inputs!C$34 | D6: =D5*Inputs!D$34 | E6: € | F6: Ingresos año 3 x múltiplo de ingresos.
A7: EBITDA mes 36 anualizado | B7: =(Socios_36M!B$39*(Inputs!B$27+Inputs!B$28)/(1+Inputs!$B$12)-Socios_36M!B$39*Inputs!B$29-Inputs!$B$16-Inputs!$B$17-Inputs!B$30)*12 | C7: =(Socios_36M!C$39*(Inputs!C$27+Inputs!C$28)/(1+Inputs!$B$12)-Socios_36M!C$39*Inputs!C$29-Inputs!$B$16-Inputs!$B$17-Inputs!C$30)*12 | D7: =(Socios_36M!D$39*(Inputs!D$27+Inputs!D$28)/(1+Inputs!$B$12)-Socios_36M!D$39*Inputs!D$29-Inputs!$B$16-Inputs!$B$17-Inputs!D$30)*12 | E7: € | F7: EBITDA mes 36 x 12.
A8: Valor por múltiplo EBITDA | B8: =MAX(0,B7)*Inputs!B$32 | C8: =MAX(0,C7)*Inputs!C$32 | D8: =MAX(0,D7)*Inputs!D$32 | E8: € | F8: EBITDA anualizado x múltiplo; si EBITDA negativo, queda en 0.
A9: Valoración sugerida pre-money | B9: =AVERAGE(B4,B6,B8) | C9: =AVERAGE(C4,C6,C8) | D9: =AVERAGE(D4,D6,D8) | E9: € | F9: Promedio simple de coste, ingresos y EBITDA.
A10: Importe inversión simulada | B10: =Inputs!$B$6 | C10: =Inputs!$B$6 | D10: =Inputs!$B$6 | E10: € | F10: Link a Inputs.
A11: Valor post-money | B11: =B9+B10 | C11: =C9+C10 | D11: =D9+D10 | E11: € | F11: Pre-money + inversión.
A12: % inversor resultante | B12: =IFERROR(B10/B11,0) | C12: =IFERROR(C10/C11,0) | D12: =IFERROR(D10/D11,0) | E12: % | F12: Inversión / post-money.

Sheet CapTable
A1: Cap table - Simulación de entrada inversor
A3: Socio / inversor | B3: % antes | C3: Valor antes | D3: Inversión nueva | E3: % nuevo inversor | F3: % después | G3: Valor post-money | H3: Nota
A4: Sergi / fundador | B4: 0.2 | C4: =B4*Inputs!$B$7 | D4: =IF(A4="Nuevo inversor",Inputs!$B$6,0) | E4: =IF(A4="Nuevo inversor",Inputs!$B$6/(Inputs!$B$7+Inputs!$B$6),0) | F4: =IF(A4="Nuevo inversor",E4,B4*(1-SUM($E$4:$E$9))) | G4: =F4*(Inputs!$B$7+Inputs!$B$6) | H4: Ejemplo editable: sustituir por reparto real.
A5: Marta | B5: 0.2 | C5: =B5*Inputs!$B$7 | D5: =IF(A5="Nuevo inversor",Inputs!$B$6,0) | E5: =IF(A5="Nuevo inversor",Inputs!$B$6/(Inputs!$B$7+Inputs!$B$6),0) | F5: =IF(A5="Nuevo inversor",E5,B5*(1-SUM($E$4:$E$9))) | G5: =F5*(Inputs!$B$7+Inputs!$B$6) | H5: Ejemplo editable.
A6: Antonio | B6: 0.2 | C6: =B6*Inputs!$B$7 | D6: =IF(A6="Nuevo inversor",Inputs!$B$6,0) | E6: =IF(A6="Nuevo inversor",Inputs!$B$6/(Inputs!$B$7+Inputs!$B$6),0) | F6: =IF(A6="Nuevo inversor",E6,B6*(1-SUM($E$4:$E$9))) | G6: =F6*(Inputs!$B$7+Inputs!$B$6) | H6: Ejemplo editable.
A7: Arnau | B7: 0.2 | C7: =B7*Inputs!$B$7 | D7: =IF(A7="Nuevo inversor",Inputs!$B$6,0) | E7: =IF(A7="Nuevo inversor",Inputs!$B$6/(Inputs!$B$7+Inputs!$B$6),0) | F7: =IF(A7="Nuevo inversor",E7,B7*(1-SUM($E$4:$E$9))) | G7: =F7*(Inputs!$B$7+Inputs!$B$6) | H7: Ejemplo editable.
A8: Óscar | B8: 0.2 | C8: =B8*Inputs!$B$7 | D8: =IF(A8="Nuevo inversor",Inputs!$B$6,0) | E8: =IF(A8="Nuevo inversor",Inputs!$B$6/(Inputs!$B$7+Inputs!$B$6),0) | F8: =IF(A8="Nuevo inversor",E8,B8*(1-SUM($E$4:$E$9))) | G8: =F8*(Inputs!$B$7+Inputs!$B$6) | H8: Ejemplo editable.
A9: Nuevo inversor | B9: 0 | C9: =B9*Inputs!$B$7 | D9: =IF(A9="Nuevo inversor",Inputs!$B$6,0) | E9: =IF(A9="Nuevo inversor",Inputs!$B$6/(Inputs!$B$7+Inputs!$B$6),0) | F9: =IF(A9="Nuevo inversor",E9,B9*(1-SUM($E$4:$E$9))) | G9: =F9*(Inputs!$B$7+Inputs!$B$6) | H9: El % se calcula con inversión / post-money.
A10: TOTAL | B10: =SUM(B4:B9) | C10: =SUM(C4:C9) | D10: =SUM(D4:D9) | E10: =SUM(E4:E9) | F10: =SUM(F4:F9) | G10: =SUM(G4:G9)

Sheet UsoFondos
A1: Uso de fondos - Solicitud financiación
A3: Partida | B3: Importe | C3: % sobre total | D3: Prioridad | E3: Comentario
A4: Climatizacion, agua y renovacion de aire | B4: 77740.09 | C4: =B4/$B$9 | D4: Alta | E4: Instalacion Carulla (clima+agua+ACS+RITE), pendiente de pago.
A5: Instalacion electrica y contraincendios | B5: 47863.32 | C5: =B5/$B$9 | D5: Alta | E5: Electrica gimnasio (Patrick), deteccion incendios, caja de contadores.
A6: Maquinaria, aduana y transporte | B6: 48788.66 | C6: =B6/$B$9 | D6: Alta | E6: IVA importacion maquinaria HSE + transporte y despacho de aduana.
A7: Vestuarios, suelo y acabados | B7: 66284.45 | C7: =B7/$B$9 | D7: Media | E7: Taquillas, suelo, pintura, espejos, material Obramat (banos/vestuarios).
A8: Accesos, rotulos y obra final | B8: 68042.99 | C8: =B8/$B$9 | D8: Media | E8: Tornos, puerta QR, elevador, rotulo, Luis Miguel (tabiques+techo), techo RF.
A9: TOTAL PENDIENTE DE PAGO | B9: =SUM(B4:B8) | C9: =SUM(C4:C8)
A10: Caja ya disponible en banco | B10: -63246 | D10: - | E10: Saldo actual en cuenta; cubre parte de la necesidad.
A11: NECESIDAD DE FINANCIACION | B11: =B9+B10 | D11: - | E11: Importe a cubrir con capital y/o prestamo (ver Inputs!B6).

Sheet Checklist
A1: Checklist para cerrar dossier de financiación e inversión
A3: Bloque | B3: Dato/documento | C3: Estado | D3: Responsable | E3: Dónde impacta | F3: Notas
A4: Sociedad | B4: Escritura, CIF/NIF, socios y participaciones reales | C4: Pendiente | D4: Sergi | E4: CapTable / Dossier | F4: Actualizar reparto real; ahora hay ejemplo editable.
A5: Nave | B5: Contrato de alquiler o documento de uso de nave | C5: Pendiente | D5: Sergi | E5: Plan de negocio | F5: CL Ensija 32, Sant Fruitós de Bages.
A6: Inversión | B6: Facturas/proformas de obra, suelo, maquinaria, LED, vestuarios | C6: Pendiente | D6: Sergi | E6: Inputs / UsoFondos | F6: Separar ya pagado vs pendiente.
A7: Financiación | B7: Préstamos de socios existentes y condiciones | C7: Pendiente | D7: Sergi | E7: Caja_Deuda | F7: Importe, interés, plazo, prioridad de cobro.
A8: Comercial | B8: Preinscripciones reales, descargas app, tarjetas activas | C8: Pendiente | D8: Sergi | E8: Socios_36M | F8: Base para defender socios iniciales.
A9: Ingresos | B9: Precio por cuota, promociones fundadores, coaching y extras | C9: Pendiente | D9: Sergi | E9: Inputs / PnL | F9: Separar precio con IVA y neto.
A10: Costes | B10: Coste mensual real estimado de alquiler/leasing, luz, agua, limpieza, seguro, app, gestoría | C10: Pendiente | D10: Sergi | E10: PnL / Caja | F10: Validar el objetivo de 10.000 €/mes.
A11: Legal | B11: Borrador pacto socios / term sheet inversor | C11: Pendiente | D11: Abogada | E11: Dossier inversor | F11: No enviar capital sin pacto de socios.
A12: Prestamista | B12: Contrato préstamo privado y calendario de pagos | C12: Pendiente | D12: Abogada/Gestor | E12: Caja_Deuda | F12: Separar deuda de entrada en capital.
A13: Valoración | B13: Revisión final de valoración pre-money y % ofrecido | C13: Pendiente | D13: Sergi | E13: Valoracion / CapTable | F13: Definir rango, no una cifra única.
